lsme/__init__.py
lsme/numeric/GranadaCapitalD_matching.py
lsme/numeric/GranadaCapitalDelta1_matching.py
lsme/numeric/GranadaCapitalDelta3_matching.py
lsme/numeric/GranadaCapitalE_matching.py
lsme/numeric/GranadaCapitalN_matching.py
lsme/numeric/GranadaCapitalOmega1_matching.py
lsme/numeric/GranadaCapitalOmega2_matching.py
lsme/numeric/GranadaCapitalOmega4_matching.py
lsme/numeric/GranadaCapitalPhi_matching.py
lsme/numeric/GranadaCapitalPi1_matching.py
lsme/numeric/GranadaCapitalPi7_matching.py
lsme/numeric/GranadaCapitalQ1_matching.py
lsme/numeric/GranadaCapitalQ5_matching.py
lsme/numeric/GranadaCapitalQ7_matching.py
lsme/numeric/GranadaCapitalS1_matching.py
lsme/numeric/GranadaCapitalS2_matching.py
lsme/numeric/GranadaCapitalS_matching.py
lsme/numeric/GranadaCapitalSigma1_matching.py
lsme/numeric/GranadaCapitalSigma_matching.py
lsme/numeric/GranadaCapitalT1_matching.py
lsme/numeric/GranadaCapitalT2_matching.py
lsme/numeric/GranadaCapitalTheta1_matching.py
lsme/numeric/GranadaCapitalTheta3_matching.py
lsme/numeric/GranadaCapitalU_matching.py
lsme/numeric/GranadaCapitalUpsilon_matching.py
lsme/numeric/GranadaCapitalXi1_matching.py
lsme/numeric/GranadaCapitalXi_matching.py
lsme/numeric/Granadaomega1_matching.py
lsme/numeric/Granadaomega2_matching.py
lsme/numeric/Granadaomega4_matching.py
lsme/numeric/Granadavarphi_matching.py
lsme/numeric/Granadazeta_matching.py
lsme/numeric/__init__.py
lsme/numeric/matchingresult.py
lsme/symbolic/__init__.py
lsme/symbolic/db.py
lsme-0.1.0.dist-info/LICENSE
lsme-0.1.0.dist-info/METADATA
lsme-0.1.0.dist-info/WHEEL
lsme-0.1.0.dist-info/top_level.txt
lsme-0.1.0.dist-info/RECORD
